MANIFEST.in
README.md
setup.cfg
setup.py
velocyto/__init__.py
velocyto/_version.py
velocyto/analysis.py
velocyto/constants.py
velocyto/counter.py
velocyto/diffusion.py
velocyto/estimation.py
velocyto/feature.py
velocyto/gene_info.py
velocyto/indexes.py
velocyto/logic.py
velocyto/metadata.py
velocyto/molitem.py
velocyto/neighbors.py
velocyto/r_interface.py
velocyto/read.py
velocyto/segment_match.py
velocyto/serialization.py
velocyto/speedboosted.c
velocyto/speedboosted.pyx
velocyto/transcript_model.py
velocyto/utils.py
velocyto.egg-info/PKG-INFO
velocyto.egg-info/SOURCES.txt
velocyto.egg-info/dependency_links.txt
velocyto.egg-info/entry_points.txt
velocyto.egg-info/requires.txt
velocyto.egg-info/top_level.txt
velocyto/commands/__init__.py
velocyto/commands/_run.py
velocyto/commands/dropest_bc_correct.py
velocyto/commands/run.py
velocyto/commands/run10x.py
velocyto/commands/run_dropest.py
velocyto/commands/run_smartseq2.py
velocyto/commands/velocyto.py