Metadata-Version: 1.1
Name: velocyto
Version: 0.17.7
Summary: RNA velocity analysis for single cell RNA-seq data
Home-page: https://github.com/velocyto-team/velocyto.py
Author: Linnarsson Lab
Author-email: sten.linnarsson@ki.se
License: BSD2
Download-URL: https://github.com/velocyto-team/velocyto.py/archive/0.17.7.tar.gz
Keywords: RNAseq,singlecell,bioinformatics,transcriptomics
Platform: UNKNOWN
